Dicthon/__init__.py
Dicthon/dictionary_api_entry.py
Dicthon-0.1.6.dist-info/METADATA
Dicthon-0.1.6.dist-info/WHEEL
Dicthon-0.1.6.dist-info/top_level.txt
Dicthon-0.1.6.dist-info/RECORD
