Metadata-Version: 2.1
Name: Dicthon
Version: 0.1.6
Summary: A dictonary library
Home-page: https://dicthon.readthedocs.io/en/
Author: Eyji Koike Cuff
Author-email: purgers.crewel-0q@icloud.com
License: MIT
Platform: UNKNOWN
Classifier: Intended Audience :: Developers
Classifier: License :: OSI Approved :: MIT License
Classifier: Programming Language :: Python
Classifier: Programming Language :: Python :: 3
Classifier: Programming Language :: Python :: 3.6
Classifier: Programming Language :: Python :: 3.7
Classifier: Programming Language :: Python :: 3.8
Classifier: Programming Language :: Python :: 3.9
Classifier: Programming Language :: Python :: 3.10
Classifier: Operating System :: OS Independent
Requires-Dist: requests
